{"college_id": "DNB0488", "college_name": "LISIE MEDICAL INSTITUTION", "yearly_trends": {"2024": {"total_seats": 0, "courses_offered": 7, "total_admissions": 38, "best_rank": 1472, "courses": {"CRS0068": {"categories": {"OPEN": {"opening": 17600, "closing": 21252, "candidates": 7}}}, "CRS0078": {"categories": {"OPEN": {"opening": 3293, "closing": 4589, "candidates": 9}}}, "CRS0079": {"categories": {"OPEN": {"opening": 14202, "closing": 15023, "candidates": 4}}}, "CRS0088": {"categories": {"OPEN": {"opening": 16512, "closing": 24074, "candidates": 6}}}, "CRS0090": {"categories": {"OPEN": {"opening": 7295, "closing": 7945, "candidates": 4}}}, "CRS0100": {"categories": {"OPEN": {"opening": 1472, "closing": 3117, "candidates": 4}}}, "CRS0120": {"categories": {"OPEN": {"opening": 12214, "closing": 20577, "candidates": 4}}}}}, "2023": {"total_seats": 0, "courses_offered": 6, "total_admissions": 35, "best_rank": 3698, "courses": {"CRS0068": {"categories": {"OPEN": {"opening": 17429, "closing": 18099, "candidates": 3}}}, "CRS0078": {"categories": {"OPEN": {"opening": 3698, "closing": 5119, "candidates": 11}}}, "CRS0079": {"categories": {"OPEN": {"opening": 12385, "closing": 16592, "candidates": 5}}}, "CRS0088": {"categories": {"OPEN": {"opening": 14373, "closing": 24143, "candidates": 6}}}, "CRS0090": {"categories": {"OPEN": {"opening": 7428, "closing": 9457, "candidates": 6}}}, "CRS0120": {"categories": {"OPEN": {"opening": 11571, "closing": 12723, "candidates": 4}}}}}}}