{"college_id": "DNB0963", "college_name": "ANKURA MEDICAL AND RESEARCH CENTRE PVTLTD ", "yearly_trends": {"2024": {"total_seats": 0, "courses_offered": 1, "total_admissions": 3, "best_rank": 12219, "courses": {"CRS0090": {"categories": {"OPEN": {"opening": 12219, "closing": 13742, "candidates": 3}}}}}, "2023": {"total_seats": 0, "courses_offered": 1, "total_admissions": 4, "best_rank": 12295, "courses": {"CRS0090": {"categories": {"OPEN": {"opening": 12295, "closing": 15078, "candidates": 4}}}}}}}