{"college_id": "DNB0253", "college_name": "UNIQUE HOSPITAL MULTISPECIALITY AND RESEARCH INSTITUTE (SURAT LIFE CARE PVT LTD)", "yearly_trends": {"2024": {"total_seats": 0, "courses_offered": 1, "total_admissions": 2, "best_rank": 12147, "courses": {"CRS0101": {"categories": {"OPEN": {"opening": 12147, "closing": 12840, "candidates": 2}}}}}, "2023": {"total_seats": 0, "courses_offered": 1, "total_admissions": 3, "best_rank": 11696, "courses": {"CRS0101": {"categories": {"OPEN": {"opening": 11696, "closing": 15239, "candidates": 3}}}}}}}