{"college_id": "DNB0452", "college_name": "ASTER MEDCITY", "yearly_trends": {"2024": {"total_seats": 0, "courses_offered": 8, "total_admissions": 30, "best_rank": 1479, "courses": {"CRS0068": {"categories": {"OPEN": {"opening": 16422, "closing": 21348, "candidates": 6}}}, "CRS0083": {"categories": {"OPEN": {"opening": 51021, "closing": 64741, "candidates": 3}}}, "CRS0084": {"categories": {"OPEN": {"opening": 10799, "closing": 15374, "candidates": 3}}}, "CRS0088": {"categories": {"OPEN": {"opening": 15359, "closing": 25668, "candidates": 4}}}, "CRS0090": {"categories": {"OPEN": {"opening": 5833, "closing": 7695, "candidates": 5}}}, "CRS0100": {"categories": {"OPEN": {"opening": 1479, "closing": 1492, "candidates": 3}}}, "CRS0101": {"categories": {"OPEN": {"opening": 6168, "closing": 10484, "candidates": 4}}}, "CRS0206": {"categories": {"OPEN": {"opening": 17953, "closing": 19817, "candidates": 2}}}}}, "2023": {"total_seats": 0, "courses_offered": 7, "total_admissions": 21, "best_rank": 1266, "courses": {"CRS0068": {"categories": {"OPEN": {"opening": 17048, "closing": 18476, "candidates": 3}}}, "CRS0084": {"categories": {"OPEN": {"opening": 9270, "closing": 17784, "candidates": 3}}}, "CRS0088": {"categories": {"OPEN": {"opening": 19854, "closing": 21347, "candidates": 2}}}, "CRS0090": {"categories": {"OPEN": {"opening": 5880, "closing": 7532, "candidates": 3}}}, "CRS0100": {"categories": {"OPEN": {"opening": 1266, "closing": 2421, "candidates": 4}}}, "CRS0101": {"categories": {"OPEN": {"opening": 8362, "closing": 10620, "candidates": 4}}}, "CRS0122": {"categories": {"OPEN": {"opening": 14890, "closing": 16540, "candidates": 2}}}}}}}