{"college_id": "MED0116", "college_name": "CENTRAL INSTITUTE OF PSYCHIATRY", "yearly_trends": {"2024": {"total_seats": 0, "courses_offered": 1, "total_admissions": 61, "best_rank": 1131, "courses": {"CRS0173": {"categories": {"EWS": {"opening": 8787, "closing": 20490, "candidates": 6}, "OBC": {"opening": 6824, "closing": 16360, "candidates": 16}, "OPEN": {"opening": 1131, "closing": 6818, "candidates": 21}, "OPEN PWD": {"opening": 87959, "closing": 120108, "candidates": 2}, "SC": {"opening": 17202, "closing": 29624, "candidates": 10}, "ST": {"opening": 18397, "closing": 44874, "candidates": 6}}}}}, "2023": {"total_seats": 0, "courses_offered": 1, "total_admissions": 57, "best_rank": 722, "courses": {"CRS0173": {"categories": {"EWS": {"opening": 7630, "closing": 11967, "candidates": 5}, "OBC": {"opening": 9477, "closing": 22022, "candidates": 17}, "OPEN": {"opening": 722, "closing": 11561, "candidates": 20}, "OPEN PWD": {"opening": 93455, "closing": 93455, "candidates": 1}, "SC": {"opening": 10726, "closing": 27252, "candidates": 10}, "ST": {"opening": 29980, "closing": 40427, "candidates": 4}}}}}}}