{"college_id": "MED0459", "college_name": "INSTITUTE OF MEDICAL SCIENCES AND SUM HOSPITAL", "yearly_trends": {"2024": {"total_seats": 0, "courses_offered": 21, "total_admissions": 243, "best_rank": 6119, "courses": {"CRS0150": {"categories": {"OPEN": {"opening": 109805, "closing": 109805, "candidates": 1}}}, "CRS0152": {"categories": {"OPEN": {"opening": 113298, "closing": 133519, "candidates": 2}}}, "CRS0154": {"categories": {"OPEN": {"opening": 49952, "closing": 70710, "candidates": 4}}}, "CRS0155": {"categories": {"OPEN": {"opening": 37555, "closing": 37555, "candidates": 1}}}, "CRS0158": {"categories": {"OPEN": {"opening": 58532, "closing": 72579, "candidates": 8}}}, "CRS0161": {"categories": {"OPEN": {"opening": 73921, "closing": 79268, "candidates": 2}}}, "CRS0164": {"categories": {"OPEN": {"opening": 79040, "closing": 87415, "candidates": 2}}}, "CRS0166": {"categories": {"OPEN": {"opening": 88736, "closing": 93185, "candidates": 3}}}, "CRS0168": {"categories": {"OPEN": {"opening": 60111, "closing": 69722, "candidates": 10}}}, "CRS0169": {"categories": {"OPEN": {"opening": 127508, "closing": 127508, "candidates": 1}}}, "CRS0171": {"categories": {"OPEN": {"opening": 142558, "closing": 166699, "candidates": 2}}}, "CRS0172": {"categories": {"OPEN": {"opening": 62513, "closing": 83662, "candidates": 2}}}, "CRS0173": {"categories": {"OPEN": {"opening": 27722, "closing": 37119, "candidates": 6}}}, "CRS0175": {"categories": {"OPEN": {"opening": 35288, "closing": 48370, "candidates": 6}}}, "CRS0177": {"categories": {"OPEN": {"opening": 89121, "closing": 89121, "candidates": 1}}}, "CRS0181": {"categories": {"OPEN": {"opening": 172038, "closing": 183824, "candidates": 2}}}, "CRS0182": {"categories": {"OPEN": {"opening": 63912, "closing": 110089, "candidates": 4}}}, "CRS0193": {"categories": {"OPEN": {"opening": 24955, "closing": 41318, "candidates": 6}}}, "CRS0194": {"categories": {"OPEN": {"opening": 70121, "closing": 74055, "candidates": 2}}}, "CRS0195": {"categories": {"OPEN": {"opening": 30371, "closing": 35043, "candidates": 6}}}, "CRS0196": {"categories": {"OPEN": {"opening": 79491, "closing": 96587, "candidates": 2}}}}}, "2023": {"total_seats": 0, "courses_offered": 20, "total_admissions": 251, "best_rank": 8377, "courses": {"CRS0150": {"categories": {"OPEN": {"opening": 115018, "closing": 115018, "candidates": 1}}}, "CRS0152": {"categories": {"OPEN": {"opening": 168973, "closing": 181695, "candidates": 2}}}, "CRS0154": {"categories": {"OPEN": {"opening": 33298, "closing": 70462, "candidates": 7}}}, "CRS0155": {"categories": {"OPEN": {"opening": 28516, "closing": 28516, "candidates": 1}}}, "CRS0158": {"categories": {"OPEN": {"opening": 26822, "closing": 85275, "candidates": 7}}}, "CRS0161": {"categories": {"OPEN": {"opening": 49335, "closing": 69566, "candidates": 2}}}, "CRS0164": {"categories": {"OPEN": {"opening": 142399, "closing": 143054, "candidates": 2}}}, "CRS0166": {"categories": {"OPEN": {"opening": 87729, "closing": 109883, "candidates": 5}}}, "CRS0168": {"categories": {"OPEN": {"opening": 53335, "closing": 93606, "candidates": 6}}}, "CRS0169": {"categories": {"OPEN": {"opening": 138384, "closing": 160974, "candidates": 2}}}, "CRS0172": {"categories": {"OPEN": {"opening": 74986, "closing": 87564, "candidates": 2}}}, "CRS0173": {"categories": {"OPEN": {"opening": 28770, "closing": 41200, "candidates": 6}}}, "CRS0175": {"categories": {"OPEN": {"opening": 40948, "closing": 68947, "candidates": 5}}}, "CRS0177": {"categories": {"OPEN": {"opening": 76329, "closing": 76329, "candidates": 1}}}, "CRS0181": {"categories": {"OPEN": {"opening": 182493, "closing": 183237, "candidates": 2}}}, "CRS0182": {"categories": {"OPEN": {"opening": 50780, "closing": 77195, "candidates": 4}}}, "CRS0193": {"categories": {"OPEN": {"opening": 133842, "closing": 133842, "candidates": 1}}}, "CRS0194": {"categories": {"OPEN": {"opening": 61611, "closing": 69318, "candidates": 2}}}, "CRS0195": {"categories": {"OPEN": {"opening": 30273, "closing": 38077, "candidates": 6}}}, "CRS0196": {"categories": {"OPEN": {"opening": 88281, "closing": 113033, "candidates": 2}}}}}}}