{"college_id": "MED0057", "college_name": "ARMED FORCES MEDICAL COLLEGE", "yearly_trends": {"2024": {"total_seats": 0, "courses_offered": 11, "total_admissions": 62, "best_rank": 17437, "courses": {"CRS0157": {"categories": {"OPEN": {"opening": 88618, "closing": 197010, "candidates": 4}}}, "CRS0158": {"categories": {"OPEN": {"opening": 63759, "closing": 116851, "candidates": 4}}}, "CRS0164": {"categories": {"OPEN": {"opening": 76103, "closing": 96778, "candidates": 8}}}, "CRS0166": {"categories": {"OPEN": {"opening": 17437, "closing": 115253, "candidates": 3}}}, "CRS0168": {"categories": {"OPEN": {"opening": 81435, "closing": 85087, "candidates": 5}}}, "CRS0169": {"categories": {"OPEN": {"opening": 91459, "closing": 91459, "candidates": 1}}}, "CRS0171": {"categories": {"OPEN": {"opening": 26280, "closing": 170247, "candidates": 9}}}, "CRS0181": {"categories": {"OPEN": {"opening": 51918, "closing": 160551, "candidates": 5}}}, "CRS0193": {"categories": {"OPEN": {"opening": 74251, "closing": 77524, "candidates": 3}}}, "CRS0194": {"categories": {"OPEN": {"opening": 22380, "closing": 70537, "candidates": 12}}}, "CRS0195": {"categories": {"OPEN": {"opening": 30434, "closing": 104237, "candidates": 8}}}}}}}