{"id": "DNB0659", "name": "SADHU VASWANI MISSIONS ", "short_name": "SADHU VASWANI MISSIONS ", "type": "DNB", "state": "MAHARASHTRA", "city": "", "management": "GOVERNMENT", "established": null, "stats": {"years_active": [2024, 2023], "courses_offered": 10}, "courses": [{"course_id": "CRS0099", "total_seats": 0, "best_rank_ever": 20789}, {"course_id": "CRS0094", "total_seats": 0, "best_rank_ever": 21452}, {"course_id": "CRS0078", "total_seats": 0, "best_rank_ever": 3303}, {"course_id": "CRS0076", "total_seats": 0, "best_rank_ever": 21452}, {"course_id": "CRS0079", "total_seats": 0, "best_rank_ever": 11481}, {"course_id": "CRS0100", "total_seats": 0, "best_rank_ever": 2338}, {"course_id": "CRS0119", "total_seats": 0, "best_rank_ever": 32682}, {"course_id": "CRS0092", "total_seats": 0, "best_rank_ever": 38193}, {"course_id": "CRS0118", "total_seats": 0, "best_rank_ever": 30981}, {"course_id": "CRS0088", "total_seats": 0, "best_rank_ever": 14869}], "cutoff_trends": {"CRS0078": {"2024": {"OPEN": {"opening": 3303, "closing": 4509}}, "2023": {"OPEN": {"opening": 3762, "closing": 5514}}}, "CRS0079": {"2024": {"OPEN": {"opening": 12108, "closing": 12521}}, "2023": {"OPEN": {"opening": 11481, "closing": 18308}}}, "CRS0088": {"2024": {"OPEN": {"opening": 14869, "closing": 18593}}, "2023": {"OPEN": {"opening": 16394, "closing": 18169}}}, "CRS0092": {"2024": {"OPEN": {"opening": 38560, "closing": 38560}}, "2023": {"OPEN": {"opening": 38193, "closing": 49701}}}, "CRS0094": {"2024": {"OPEN": {"opening": 23097, "closing": 26327}}, "2023": {"OPEN": {"opening": 21452, "closing": 25514}}}, "CRS0099": {"2024": {"OPEN": {"opening": 20789, "closing": 23995}}, "2023": {"OPEN": {"opening": 26873, "closing": 32464}}}, "CRS0100": {"2024": {"OPEN": {"opening": 2338, "closing": 2338}}, "2023": {"OPEN": {"opening": 2494, "closing": 2535}}}, "CRS0118": {"2024": {"OPEN": {"opening": 30981, "closing": 38077}}, "2023": {"OPEN": {"opening": 32424, "closing": 42141}}}, "CRS0119": {"2024": {"OPEN": {"opening": 32682, "closing": 35729}}, "2023": {"OPEN": {"opening": 39597, "closing": 39597}}}, "CRS0076": {"2023": {"OPEN": {"opening": 21452, "closing": 21452}}}}, "seat_availability": {}, "highlights": {"best_overall_rank": 2338}}