{"id": "DNB0258", "name": "ALCHEMIST HOSPITAL", "short_name": "ALCHEMIST HOSPITAL", "type": "DNB", "state": "HARYANA", "city": "", "management": "GOVERNMENT", "established": null, "stats": {"years_active": [2024, 2023], "courses_offered": 1}, "courses": [{"course_id": "CRS0125", "total_seats": 0, "best_rank_ever": 15048}], "cutoff_trends": {"CRS0125": {"2024": {"OPEN": {"opening": 19559, "closing": 34201}}, "2023": {"OPEN": {"opening": 15048, "closing": 32535}}}}, "seat_availability": {}, "highlights": {"best_overall_rank": 15048}}