{"id": "DNB1068", "name": "GANGASHEEL ADVANCED MEDICAL RESEARCH INSTITUTE", "short_name": "GANGASHEEL ADVANCED MEDICAL RESEARCH INSTITUTE", "type": "DNB", "state": "UTTAR PRADESH", "city": "", "management": "GOVERNMENT", "established": null, "stats": {"years_active": [2024, 2023], "courses_offered": 4}, "courses": [{"course_id": "CRS0021", "total_seats": 0, "best_rank_ever": 29271}, {"course_id": "CRS0120", "total_seats": 0, "best_rank_ever": 26557}, {"course_id": "CRS0123", "total_seats": 0, "best_rank_ever": 21329}, {"course_id": "CRS0118", "total_seats": 0, "best_rank_ever": 43809}], "cutoff_trends": {"CRS0021": {"2024": {"OPEN": {"opening": 29271, "closing": 29271}}}, "CRS0120": {"2024": {"OPEN": {"opening": 26557, "closing": 28131}}, "2023": {"OPEN": {"opening": 31376, "closing": 31659}}}, "CRS0118": {"2023": {"OPEN": {"opening": 43809, "closing": 55338}}}, "CRS0123": {"2023": {"OPEN": {"opening": 21329, "closing": 34687}}}}, "seat_availability": {}, "highlights": {"best_overall_rank": 21329}}