{"id": "DNB1033", "name": "YASHODA HOSPITAL", "short_name": "YASHODA HOSPITAL", "type": "DNB", "state": "TELANGANA", "city": "", "management": "GOVERNMENT", "established": null, "stats": {"years_active": [2024, 2023], "courses_offered": 14}, "courses": [{"course_id": "CRS0084", "total_seats": 0, "best_rank_ever": 10015}, {"course_id": "CRS0120", "total_seats": 0, "best_rank_ever": 9283}, {"course_id": "CRS0123", "total_seats": 0, "best_rank_ever": 19706}, {"course_id": "CRS0122", "total_seats": 0, "best_rank_ever": 23293}, {"course_id": "CRS0099", "total_seats": 0, "best_rank_ever": 12804}, {"course_id": "CRS0074", "total_seats": 0, "best_rank_ever": 13279}, {"course_id": "CRS0068", "total_seats": 0, "best_rank_ever": 16479}, {"course_id": "CRS0071", "total_seats": 0, "best_rank_ever": 17611}, {"course_id": "CRS0100", "total_seats": 0, "best_rank_ever": 1732}, {"course_id": "CRS0207", "total_seats": 0, "best_rank_ever": 24754}, {"course_id": "CRS0206", "total_seats": 0, "best_rank_ever": 20216}, {"course_id": "CRS0101", "total_seats": 0, "best_rank_ever": 9928}, {"course_id": "CRS0088", "total_seats": 0, "best_rank_ever": 20018}, {"course_id": "CRS0090", "total_seats": 0, "best_rank_ever": 7867}], "cutoff_trends": {"CRS0068": {"2024": {"OPEN": {"opening": 17867, "closing": 24667}}, "2023": {"OPEN": {"opening": 16479, "closing": 22820}}}, "CRS0071": {"2024": {"OPEN": {"opening": 17611, "closing": 27176}}, "2023": {"OPEN": {"opening": 19001, "closing": 31076}}}, "CRS0074": {"2024": {"OPEN": {"opening": 14678, "closing": 17947}}, "2023": {"OPEN": {"opening": 13279, "closing": 17306}}}, "CRS0084": {"2024": {"OPEN": {"opening": 11102, "closing": 16711}}, "2023": {"OPEN": {"opening": 10015, "closing": 10015}}}, "CRS0088": {"2024": {"OPEN": {"opening": 22061, "closing": 23786}}, "2023": {"OPEN": {"opening": 20018, "closing": 20018}}}, "CRS0090": {"2024": {"OPEN": {"opening": 7925, "closing": 11100}}, "2023": {"OPEN": {"opening": 7867, "closing": 8636}}}, "CRS0099": {"2024": {"OPEN": {"opening": 12804, "closing": 23574}}}, "CRS0100": {"2024": {"OPEN": {"opening": 1732, "closing": 1732}}, "2023": {"OPEN": {"opening": 1971, "closing": 2613}}}, "CRS0101": {"2024": {"OPEN": {"opening": 10716, "closing": 12691}}, "2023": {"OPEN": {"opening": 9928, "closing": 11096}}}, "CRS0120": {"2024": {"OPEN": {"opening": 9283, "closing": 12827}}, "2023": {"OPEN": {"opening": 9587, "closing": 9587}}}, "CRS0123": {"2024": {"OPEN": {"opening": 19706, "closing": 22342}}, "2023": {"OPEN": {"opening": 21426, "closing": 21426}}}, "CRS0206": {"2024": {"OPEN": {"opening": 20216, "closing": 23439}}}, "CRS0207": {"2024": {"OPEN": {"opening": 24754, "closing": 24754}}}, "CRS0122": {"2023": {"OPEN": {"opening": 23293, "closing": 23966}}}}, "seat_availability": {}, "highlights": {"best_overall_rank": 1732}}