{"id": "MED0316", "name": "GOVERNMENT MEDICAL COLLEGE", "short_name": "GOVERNMENT MEDICAL COLLEGE", "type": "MEDICAL", "state": "KERALA", "city": "", "management": "GOVERNMENT", "established": null, "stats": {"years_active": [2024, 2023], "courses_offered": 24}, "courses": [{"course_id": "CRS0150", "total_seats": 0, "best_rank_ever": 2871}, {"course_id": "CRS0182", "total_seats": 0, "best_rank_ever": 597}, {"course_id": "CRS0154", "total_seats": 0, "best_rank_ever": 177}, {"course_id": "CRS0174", "total_seats": 0, "best_rank_ever": 13087}, {"course_id": "CRS0169", "total_seats": 0, "best_rank_ever": 25216}, {"course_id": "CRS0171", "total_seats": 0, "best_rank_ever": 34285}, {"course_id": "CRS0155", "total_seats": 0, "best_rank_ever": 1919}, {"course_id": "CRS0173", "total_seats": 0, "best_rank_ever": 3284}, {"course_id": "CRS0181", "total_seats": 0, "best_rank_ever": 42582}, {"course_id": "CRS0164", "total_seats": 0, "best_rank_ever": 8390}, {"course_id": "CRS0196", "total_seats": 0, "best_rank_ever": 2129}, {"course_id": "CRS0166", "total_seats": 0, "best_rank_ever": 58}, {"course_id": "CRS0152", "total_seats": 0, "best_rank_ever": 59716}, {"course_id": "CRS0158", "total_seats": 0, "best_rank_ever": 26}, {"course_id": "CRS0168", "total_seats": 0, "best_rank_ever": 3801}, {"course_id": "CRS0195", "total_seats": 0, "best_rank_ever": 5137}, {"course_id": "CRS0177", "total_seats": 0, "best_rank_ever": 1480}, {"course_id": "CRS0175", "total_seats": 0, "best_rank_ever": 19}, {"course_id": "CRS0193", "total_seats": 0, "best_rank_ever": 3113}, {"course_id": "CRS0172", "total_seats": 0, "best_rank_ever": 9949}, {"course_id": "CRS0157", "total_seats": 0, "best_rank_ever": 27097}, {"course_id": "CRS0194", "total_seats": 0, "best_rank_ever": 1211}, {"course_id": "CRS0170", "total_seats": 0, "best_rank_ever": 1314}, {"course_id": "CRS0156", "total_seats": 0, "best_rank_ever": 3254}], "cutoff_trends": {"CRS0150": {"2024": {"EWS": {"opening": 21135, "closing": 26148}, "OBC": {"opening": 8671, "closing": 13746}, "OPEN": {"opening": 4707, "closing": 11808}, "SC": {"opening": 18249, "closing": 26323}, "ST": {"opening": 54274, "closing": 54274}}, "2023": {"EWS": {"opening": 21131, "closing": 21131}, "OBC": {"opening": 8633, "closing": 11379}, "OPEN": {"opening": 2871, "closing": 16621}, "OPEN PWD": {"opening": 78878, "closing": 78878}, "SC": {"opening": 21210, "closing": 32594}, "ST": {"opening": 58304, "closing": 64895}}}, "CRS0152": {"2024": {"SC": {"opening": 94294, "closing": 135429}}, "2023": {"OBC": {"opening": 59716, "closing": 59716}}}, "CRS0154": {"2024": {"OBC": {"opening": 806, "closing": 806}, "OPEN": {"opening": 600, "closing": 924}}, "2023": {"EWS": {"opening": 3235, "closing": 4721}, "OBC": {"opening": 442, "closing": 442}, "OPEN": {"opening": 177, "closing": 177}, "SC": {"opening": 4803, "closing": 6537}}}, "CRS0155": {"2024": {"OBC": {"opening": 2976, "closing": 2976}}, "2023": {"OPEN": {"opening": 1919, "closing": 2973}}}, "CRS0156": {"2024": {"OPEN": {"opening": 3254, "closing": 8671}}, "2023": {"ST": {"opening": 40827, "closing": 77721}}}, "CRS0157": {"2024": {"SC": {"opening": 47340, "closing": 59554}}, "2023": {"OBC": {"opening": 35678, "closing": 58309}, "OPEN": {"opening": 27097, "closing": 60982}}}, "CRS0158": {"2024": {"EWS": {"opening": 642, "closing": 4033}, "OBC": {"opening": 543, "closing": 792}, "OPEN": {"opening": 54, "closing": 643}, "SC": {"opening": 8633, "closing": 16619}, "ST": {"opening": 18025, "closing": 27885}}, "2023": {"EWS": {"opening": 1121, "closing": 1121}, "OBC": {"opening": 200, "closing": 220}, "OPEN": {"opening": 26, "closing": 138}, "SC": {"opening": 10020, "closing": 11433}}}, "CRS0164": {"2024": {"OPEN": {"opening": 21057, "closing": 21057}, "ST": {"opening": 65800, "closing": 186677}}, "2023": {"OPEN": {"opening": 8390, "closing": 35329}}}, "CRS0166": {"2024": {"EWS": {"opening": 4571, "closing": 8938}, "OBC": {"opening": 1841, "closing": 2191}, "OPEN": {"opening": 58, "closing": 2635}, "SC": {"opening": 10775, "closing": 16442}, "ST": {"opening": 32266, "closing": 41257}}, "2023": {"OBC": {"opening": 1251, "closing": 3509}, "OPEN": {"opening": 144, "closing": 2496}, "SC": {"opening": 1275, "closing": 1275}, "ST": {"opening": 13609, "closing": 39333}}}, "CRS0168": {"2024": {"OBC": {"opening": 16767, "closing": 20130}, "OPEN": {"opening": 8559, "closing": 18613}}, "2023": {"EWS": {"opening": 37678, "closing": 69797}, "OBC": {"opening": 12977, "closing": 73122}, "OPEN": {"opening": 3801, "closing": 61564}, "SC": {"opening": 36620, "closing": 44697}}}, "CRS0169": {"2024": {"SC": {"opening": 74745, "closing": 83001}}, "2023": {"OPEN": {"opening": 25216, "closing": 25216}}}, "CRS0170": {"2024": {"OBC": {"opening": 7572, "closing": 7572}, "OPEN": {"opening": 1314, "closing": 10078}}, "2023": {"EWS": {"opening": 11386, "closing": 48045}, "SC": {"opening": 23708, "closing": 23708}, "ST": {"opening": 60584, "closing": 60584}}}, "CRS0171": {"2024": {"EWS": {"opening": 104824, "closing": 104824}, "OPEN": {"opening": 48919, "closing": 98228}, "SC": {"opening": 141994, "closing": 141994}}, "2023": {"OPEN": {"opening": 34285, "closing": 42352}}}, "CRS0172": {"2024": {"OBC": {"opening": 37743, "closing": 37743}, "SC": {"opening": 27343, "closing": 52291}}, "2023": {"OBC": {"opening": 20365, "closing": 27357}, "OPEN": {"opening": 9949, "closing": 19426}}}, "CRS0173": {"2024": {"OPEN": {"opening": 3284, "closing": 10002}}, "2023": {"OBC": {"opening": 11562, "closing": 13526}, "OPEN": {"opening": 6391, "closing": 6391}}}, "CRS0174": {"2024": {"EWS": {"opening": 26274, "closing": 26274}, "OPEN": {"opening": 13087, "closing": 13087}}, "2023": {"OBC": {"opening": 14870, "closing": 26492}, "OPEN": {"opening": 14317, "closing": 15108}}}, "CRS0175": {"2024": {"OBC": {"opening": 147, "closing": 367}, "OPEN": {"opening": 19, "closing": 19}, "SC": {"opening": 3683, "closing": 3683}, "ST": {"opening": 10841, "closing": 10841}}, "2023": {"EWS": {"opening": 476, "closing": 476}, "OBC": {"opening": 450, "closing": 450}, "OPEN": {"opening": 83, "closing": 564}, "SC": {"opening": 2216, "closing": 2216}}}, "CRS0177": {"2024": {"OBC": {"opening": 2973, "closing": 4693}, "OPEN": {"opening": 1480, "closing": 2525}, "SC": {"opening": 16619, "closing": 18249}}, "2023": {"OBC": {"opening": 2442, "closing": 2442}, "OPEN": {"opening": 2255, "closing": 2450}, "SC": {"opening": 17584, "closing": 17584}, "ST": {"opening": 56491, "closing": 56491}}}, "CRS0181": {"2024": {"OPEN": {"opening": 42582, "closing": 120129}}, "2023": {"OBC": {"opening": 61185, "closing": 68046}, "OPEN": {"opening": 52738, "closing": 88289}}}, "CRS0182": {"2024": {"EWS": {"opening": 7488, "closing": 11212}, "OBC": {"opening": 3264, "closing": 8443}, "OPEN": {"opening": 742, "closing": 8203}, "SC": {"opening": 12130, "closing": 30297}, "ST": {"opening": 40697, "closing": 47166}}, "2023": {"EWS": {"opening": 7139, "closing": 9565}, "OBC": {"opening": 3269, "closing": 5056}, "OPEN": {"opening": 597, "closing": 5696}, "SC": {"opening": 14879, "closing": 22364}, "ST": {"opening": 36330, "closing": 50221}}}, "CRS0193": {"2024": {"OBC": {"opening": 8237, "closing": 9113}, "OPEN": {"opening": 3113, "closing": 8493}}, "2023": {"OBC": {"opening": 9847, "closing": 11441}, "OPEN": {"opening": 3892, "closing": 10938}, "SC": {"opening": 24746, "closing": 24746}}}, "CRS0194": {"2024": {"EWS": {"opening": 6484, "closing": 6484}, "OBC": {"opening": 3253, "closing": 6600}, "OPEN": {"opening": 1211, "closing": 5610}, "SC": {"opening": 13476, "closing": 24032}}, "2023": {"EWS": {"opening": 7905, "closing": 9364}, "OBC": {"opening": 2205, "closing": 2838}, "OPEN": {"opening": 1270, "closing": 1462}, "SC": {"opening": 8590, "closing": 20326}, "ST": {"opening": 26869, "closing": 26869}}}, "CRS0195": {"2024": {"EWS": {"opening": 22412, "closing": 22412}, "OBC": {"opening": 7701, "closing": 8299}, "OPEN": {"opening": 5137, "closing": 5137}, "OPEN PWD": {"opening": 188593, "closing": 188593}}, "2023": {"EWS": {"opening": 14381, "closing": 25468}, "OBC": {"opening": 8827, "closing": 8827}, "OPEN": {"opening": 6937, "closing": 10448}}}, "CRS0196": {"2024": {"EWS": {"opening": 12231, "closing": 20084}, "OBC": {"opening": 5906, "closing": 7834}, "OPEN": {"opening": 3038, "closing": 4971}, "SC": {"opening": 14210, "closing": 14210}}, "2023": {"EWS": {"opening": 10816, "closing": 10816}, "OBC": {"opening": 2495, "closing": 2495}, "OPEN": {"opening": 2129, "closing": 2129}, "SC": {"opening": 16363, "closing": 24939}, "ST": {"opening": 48717, "closing": 61584}}}}, "seat_availability": {}, "highlights": {"best_overall_rank": 19}}