{"id": "DNB0728", "name": "AMANDEEP HOSPITAL", "short_name": "AMANDEEP HOSPITAL", "type": "DNB", "state": "PUNJAB", "city": "", "management": "GOVERNMENT", "established": null, "stats": {"years_active": [2024, 2023], "courses_offered": 3}, "courses": [{"course_id": "CRS0119", "total_seats": 0, "best_rank_ever": 28477}, {"course_id": "CRS0118", "total_seats": 0, "best_rank_ever": 36251}, {"course_id": "CRS0088", "total_seats": 0, "best_rank_ever": 18273}], "cutoff_trends": {"CRS0088": {"2024": {"OPEN": {"opening": 18916, "closing": 26007}}, "2023": {"OPEN": {"opening": 18273, "closing": 24331}}}, "CRS0118": {"2024": {"OPEN": {"opening": 37128, "closing": 46115}}, "2023": {"OPEN": {"opening": 36251, "closing": 54860}}}, "CRS0119": {"2024": {"OPEN": {"opening": 33209, "closing": 53834}}, "2023": {"OPEN": {"opening": 28477, "closing": 62890}}}}, "seat_availability": {}, "highlights": {"best_overall_rank": 18273}}