{"id": "DNB0521", "name": "SP FORT HOSPITAL", "short_name": "SP FORT HOSPITAL", "type": "DNB", "state": "KERALA", "city": "", "management": "GOVERNMENT", "established": null, "stats": {"years_active": [2024, 2023], "courses_offered": 2}, "courses": [{"course_id": "CRS0068", "total_seats": 0, "best_rank_ever": 22208}, {"course_id": "CRS0088", "total_seats": 0, "best_rank_ever": 20946}], "cutoff_trends": {"CRS0068": {"2024": {"OPEN": {"opening": 22208, "closing": 26753}}}, "CRS0088": {"2024": {"OPEN": {"opening": 24710, "closing": 26203}}, "2023": {"OPEN": {"opening": 20946, "closing": 25137}}}}, "seat_availability": {}, "highlights": {"best_overall_rank": 20946}}