{"id": "DNB0102", "name": "RUBAN MEMORIAL HOSPITAL", "short_name": "RUBAN MEMORIAL HOSPITAL", "type": "DNB", "state": "BIHAR", "city": "", "management": "GOVERNMENT", "established": null, "stats": {"years_active": [2024, 2023], "courses_offered": 5}, "courses": [{"course_id": "CRS0079", "total_seats": 0, "best_rank_ever": 18548}, {"course_id": "CRS0068", "total_seats": 0, "best_rank_ever": 22852}, {"course_id": "CRS0100", "total_seats": 0, "best_rank_ever": 3644}, {"course_id": "CRS0118", "total_seats": 0, "best_rank_ever": 37456}, {"course_id": "CRS0088", "total_seats": 0, "best_rank_ever": 18047}], "cutoff_trends": {"CRS0068": {"2024": {"OPEN": {"opening": 22852, "closing": 26360}}, "2023": {"OPEN": {"opening": 29818, "closing": 33440}}}, "CRS0079": {"2024": {"OPEN": {"opening": 18548, "closing": 21063}}, "2023": {"OPEN": {"opening": 20189, "closing": 23131}}}, "CRS0088": {"2024": {"OPEN": {"opening": 18213, "closing": 19050}}, "2023": {"OPEN": {"opening": 18047, "closing": 18047}}}, "CRS0100": {"2024": {"OPEN": {"opening": 3644, "closing": 3972}}}, "CRS0118": {"2024": {"OPEN": {"opening": 37456, "closing": 43424}}, "2023": {"OPEN": {"opening": 44961, "closing": 49858}}}}, "seat_availability": {}, "highlights": {"best_overall_rank": 3644}}