{"id": "MED0764", "name": "SHRI B M PATIL MEDICAL COLLEGE HOSPITAL AND RESEARCH CENTRE", "short_name": "SHRI B M PATIL MEDICAL COLLEGE HOSPITAL AND RESEARCH CENTRE", "type": "MEDICAL", "state": "KARNATAKA", "city": "", "management": "GOVERNMENT", "established": null, "stats": {"years_active": [2024, 2023], "courses_offered": 22}, "courses": [{"course_id": "CRS0150", "total_seats": 0, "best_rank_ever": 47255}, {"course_id": "CRS0182", "total_seats": 0, "best_rank_ever": 29615}, {"course_id": "CRS0159", "total_seats": 0, "best_rank_ever": 31822}, {"course_id": "CRS0154", "total_seats": 0, "best_rank_ever": 16476}, {"course_id": "CRS0169", "total_seats": 0, "best_rank_ever": 77274}, {"course_id": "CRS0171", "total_seats": 0, "best_rank_ever": 188335}, {"course_id": "CRS0155", "total_seats": 0, "best_rank_ever": 27605}, {"course_id": "CRS0173", "total_seats": 0, "best_rank_ever": 43574}, {"course_id": "CRS0181", "total_seats": 0, "best_rank_ever": 178355}, {"course_id": "CRS0164", "total_seats": 0, "best_rank_ever": 136494}, {"course_id": "CRS0196", "total_seats": 0, "best_rank_ever": 46499}, {"course_id": "CRS0166", "total_seats": 0, "best_rank_ever": 29927}, {"course_id": "CRS0152", "total_seats": 0, "best_rank_ever": 153918}, {"course_id": "CRS0158", "total_seats": 0, "best_rank_ever": 19825}, {"course_id": "CRS0168", "total_seats": 0, "best_rank_ever": 70795}, {"course_id": "CRS0195", "total_seats": 0, "best_rank_ever": 36565}, {"course_id": "CRS0177", "total_seats": 0, "best_rank_ever": 22412}, {"course_id": "CRS0175", "total_seats": 0, "best_rank_ever": 13907}, {"course_id": "CRS0193", "total_seats": 0, "best_rank_ever": 41238}, {"course_id": "CRS0172", "total_seats": 0, "best_rank_ever": 118424}, {"course_id": "CRS0157", "total_seats": 0, "best_rank_ever": 100099}, {"course_id": "CRS0194", "total_seats": 0, "best_rank_ever": 39679}], "cutoff_trends": {"CRS0150": {"2024": {"OPEN": {"opening": 47255, "closing": 72523}}, "2023": {"OPEN": {"opening": 48549, "closing": 69225}}}, "CRS0152": {"2024": {"OPEN": {"opening": 201979, "closing": 201979}}, "2023": {"OPEN": {"opening": 153918, "closing": 190277}}}, "CRS0154": {"2024": {"OPEN": {"opening": 16476, "closing": 67606}}, "2023": {"OPEN": {"opening": 16953, "closing": 61916}}}, "CRS0155": {"2024": {"OPEN": {"opening": 36445, "closing": 40595}}, "2023": {"OPEN": {"opening": 27605, "closing": 38641}}}, "CRS0157": {"2024": {"OPEN": {"opening": 100099, "closing": 184633}}, "2023": {"OPEN": {"opening": 156894, "closing": 169285}}}, "CRS0158": {"2024": {"OPEN": {"opening": 19825, "closing": 96631}}, "2023": {"OPEN": {"opening": 23533, "closing": 88414}}}, "CRS0159": {"2024": {"OPEN": {"opening": 36879, "closing": 42426}}, "2023": {"OPEN": {"opening": 31822, "closing": 32705}}}, "CRS0164": {"2024": {"OPEN": {"opening": 136494, "closing": 140618}}, "2023": {"OPEN": {"opening": 161451, "closing": 186042}}}, "CRS0166": {"2024": {"OPEN": {"opening": 31410, "closing": 80565}}, "2023": {"OPEN": {"opening": 29927, "closing": 95581}}}, "CRS0168": {"2024": {"OPEN": {"opening": 70795, "closing": 177536}}, "2023": {"OPEN": {"opening": 79675, "closing": 199035}}}, "CRS0169": {"2024": {"OPEN": {"opening": 77274, "closing": 145237}}, "2023": {"OPEN": {"opening": 170736, "closing": 182958}}}, "CRS0172": {"2024": {"OPEN": {"opening": 118424, "closing": 168689}}, "2023": {"OPEN": {"opening": 127365, "closing": 200429}}}, "CRS0173": {"2024": {"OPEN": {"opening": 43574, "closing": 49092}}, "2023": {"OPEN": {"opening": 48550, "closing": 54318}}}, "CRS0175": {"2024": {"OPEN": {"opening": 18048, "closing": 48545}}, "2023": {"OPEN": {"opening": 13907, "closing": 57085}}}, "CRS0177": {"2024": {"OPEN": {"opening": 26167, "closing": 35986}}, "2023": {"OPEN": {"opening": 22412, "closing": 38760}}}, "CRS0182": {"2024": {"OPEN": {"opening": 30277, "closing": 87296}}, "2023": {"OPEN": {"opening": 29615, "closing": 103015}}}, "CRS0193": {"2024": {"OPEN": {"opening": 43087, "closing": 57353}}, "2023": {"OPEN": {"opening": 41238, "closing": 60224}}}, "CRS0194": {"2024": {"OPEN": {"opening": 46097, "closing": 110531}}, "2023": {"OPEN": {"opening": 39679, "closing": 132452}}}, "CRS0195": {"2024": {"OPEN": {"opening": 36565, "closing": 47137}}, "2023": {"OPEN": {"opening": 38077, "closing": 46126}}}, "CRS0196": {"2024": {"OPEN": {"opening": 46499, "closing": 85883}}, "2023": {"OPEN": {"opening": 48916, "closing": 118138}}}, "CRS0171": {"2023": {"OPEN": {"opening": 188335, "closing": 191803}}}, "CRS0181": {"2023": {"OPEN": {"opening": 178355, "closing": 197603}}}}, "seat_availability": {}, "highlights": {"best_overall_rank": 13907}}