{"college_id": "DNB0152", "college_name": "ESI HOSPITAL", "yearly_trends": {"2024": {"total_seats": 0, "courses_offered": 5, "total_admissions": 7, "best_rank": 5058, "courses": {"CRS0078": {"categories": {"OPEN": {"opening": 5058, "closing": 5058, "candidates": 1}}}, "CRS0121": {"categories": {"OPEN": {"opening": 34337, "closing": 34337, "candidates": 1}}}, "CRS0123": {"categories": {"OBC": {"opening": 16567, "closing": 16567, "candidates": 1}, "SC": {"opening": 46986, "closing": 49669, "candidates": 2}}}, "CRS0125": {"categories": {"OBC": {"opening": 30754, "closing": 30754, "candidates": 1}}}, "CRS0206": {"categories": {"OPEN": {"opening": 34065, "closing": 34065, "candidates": 1}}}}}, "2023": {"total_seats": 0, "courses_offered": 9, "total_admissions": 23, "best_rank": 7401, "courses": {"CRS0068": {"categories": {"OBC": {"opening": 21293, "closing": 25728, "candidates": 2}}}, "CRS0078": {"categories": {"SC": {"opening": 22744, "closing": 22772, "candidates": 2}}}, "CRS0088": {"categories": {"ST": {"opening": 59532, "closing": 59532, "candidates": 1}}}, "CRS0090": {"categories": {"OPEN": {"opening": 7401, "closing": 8434, "candidates": 2}}}, "CRS0120": {"categories": {"OBC": {"opening": 17671, "closing": 20322, "candidates": 2}, "OPEN": {"opening": 9160, "closing": 16258, "candidates": 2}}}, "CRS0121": {"categories": {"OBC": {"opening": 35485, "closing": 44175, "candidates": 2}}}, "CRS0122": {"categories": {"SC": {"opening": 61306, "closing": 63193, "candidates": 2}}}, "CRS0123": {"categories": {"EWS": {"opening": 22383, "closing": 26242, "candidates": 2}, "OPEN": {"opening": 17770, "closing": 21337, "candidates": 2}}}, "CRS0125": {"categories": {"OBC": {"opening": 21721, "closing": 33079, "candidates": 4}}}}}}}