{"college_id": "DNB0583", "college_name": "BHAKTIVEDANTA HOSPITAL AND RESEARCH INSTITUTE", "yearly_trends": {"2024": {"total_seats": 0, "courses_offered": 6, "total_admissions": 26, "best_rank": 4325, "courses": {"CRS0068": {"categories": {"OPEN": {"opening": 22491, "closing": 26925, "candidates": 3}}}, "CRS0078": {"categories": {"OPEN": {"opening": 4325, "closing": 4680, "candidates": 4}}}, "CRS0087": {"categories": {"OPEN": {"opening": 15897, "closing": 25877, "candidates": 7}}}, "CRS0090": {"categories": {"OPEN": {"opening": 10340, "closing": 17141, "candidates": 7}}}, "CRS0120": {"categories": {"OPEN": {"opening": 10171, "closing": 11290, "candidates": 2}}}, "CRS0124": {"categories": {"OPEN": {"opening": 6154, "closing": 7799, "candidates": 3}}}}}, "2023": {"total_seats": 0, "courses_offered": 6, "total_admissions": 25, "best_rank": 4605, "courses": {"CRS0078": {"categories": {"OPEN": {"opening": 4605, "closing": 6255, "candidates": 5}}}, "CRS0087": {"categories": {"OPEN": {"opening": 15806, "closing": 20356, "candidates": 4}}}, "CRS0090": {"categories": {"OPEN": {"opening": 11522, "closing": 13628, "candidates": 5}}}, "CRS0119": {"categories": {"OPEN": {"opening": 17764, "closing": 39649, "candidates": 5}}}, "CRS0120": {"categories": {"OPEN": {"opening": 11990, "closing": 13312, "candidates": 3}}}, "CRS0124": {"categories": {"OPEN": {"opening": 5596, "closing": 6786, "candidates": 3}}}}}}}