{"college_id": "DNB0006", "college_name": "APL AND ANR AREA", "yearly_trends": {"2024": {"total_seats": 0, "courses_offered": 2, "total_admissions": 19, "best_rank": 39265, "courses": {"CRS0118": {"categories": {"OBC": {"opening": 40063, "closing": 44994, "candidates": 3}, "OPEN": {"opening": 39265, "closing": 43088, "candidates": 2}}}, "CRS0119": {"categories": {"OBC": {"opening": 46641, "closing": 57567, "candidates": 4}, "OPEN": {"opening": 39760, "closing": 49045, "candidates": 2}, "SC": {"opening": 61272, "closing": 92137, "candidates": 5}, "ST": {"opening": 117592, "closing": 142883, "candidates": 3}}}}}, "2023": {"total_seats": 0, "courses_offered": 2, "total_admissions": 18, "best_rank": 34909, "courses": {"CRS0118": {"categories": {"OPEN": {"opening": 37104, "closing": 48712, "candidates": 3}}}, "CRS0119": {"categories": {"OBC": {"opening": 43112, "closing": 78594, "candidates": 5}, "OPEN": {"opening": 34909, "closing": 74001, "candidates": 5}, "SC": {"opening": 56470, "closing": 127687, "candidates": 5}}}}}}}