{"college_id": "MED0378", "college_name": "GOVERNMENT MEDICAL COLLEGE", "yearly_trends": {"2024": {"total_seats": 0, "courses_offered": 9, "total_admissions": 60, "best_rank": 1905, "courses": {"CRS0150": {"categories": {"OBC": {"opening": 14647, "closing": 19730, "candidates": 2}, "OPEN": {"opening": 13949, "closing": 19351, "candidates": 3}, "SC": {"opening": 30824, "closing": 39510, "candidates": 3}}}, "CRS0155": {"categories": {"ST": {"opening": 54206, "closing": 70160, "candidates": 3}}}, "CRS0158": {"categories": {"EWS": {"opening": 5063, "closing": 7312, "candidates": 3}, "OBC": {"opening": 2413, "closing": 3962, "candidates": 3}, "OPEN": {"opening": 1905, "closing": 3764, "candidates": 6}}}, "CRS0166": {"categories": {"EWS": {"opening": 8049, "closing": 13010, "candidates": 3}, "OBC": {"opening": 4548, "closing": 6454, "candidates": 3}, "OPEN": {"opening": 3775, "closing": 6322, "candidates": 3}}}, "CRS0173": {"categories": {"OPEN": {"opening": 15008, "closing": 17014, "candidates": 2}}}, "CRS0181": {"categories": {"OPEN": {"opening": 49288, "closing": 92783, "candidates": 3}}}, "CRS0182": {"categories": {"OBC": {"opening": 7332, "closing": 9412, "candidates": 2}, "OPEN": {"opening": 7079, "closing": 11617, "candidates": 6}, "SC": {"opening": 22733, "closing": 31328, "candidates": 3}}}, "CRS0194": {"categories": {"OBC": {"opening": 8160, "closing": 12929, "candidates": 2}, "OPEN": {"opening": 6371, "closing": 12744, "candidates": 4}, "SC": {"opening": 26100, "closing": 44530, "candidates": 4}}}, "CRS0196": {"categories": {"ST": {"opening": 56633, "closing": 65077, "candidates": 2}}}}}, "2023": {"total_seats": 0, "courses_offered": 9, "total_admissions": 57, "best_rank": 1822, "courses": {"CRS0150": {"categories": {"EWS": {"opening": 22959, "closing": 30662, "candidates": 3}, "OPEN": {"opening": 10353, "closing": 18036, "candidates": 6}}}, "CRS0155": {"categories": {"OBC": {"opening": 9240, "closing": 10353, "candidates": 3}}}, "CRS0158": {"categories": {"OBC": {"opening": 2245, "closing": 3284, "candidates": 3}, "OPEN": {"opening": 1822, "closing": 2914, "candidates": 2}, "SC": {"opening": 11016, "closing": 13261, "candidates": 2}, "ST": {"opening": 30448, "closing": 45951, "candidates": 3}}}, "CRS0166": {"categories": {"EWS": {"opening": 7948, "closing": 10095, "candidates": 3}, "OBC": {"opening": 3007, "closing": 4064, "candidates": 2}, "ST": {"opening": 42882, "closing": 50271, "candidates": 3}}}, "CRS0173": {"categories": {"OPEN": {"opening": 9926, "closing": 18198, "candidates": 3}}}, "CRS0181": {"categories": {"OBC": {"opening": 40599, "closing": 88408, "candidates": 3}}}, "CRS0182": {"categories": {"OBC": {"opening": 5293, "closing": 7145, "candidates": 3}, "OPEN": {"opening": 3368, "closing": 6995, "candidates": 6}}}, "CRS0194": {"categories": {"EWS": {"opening": 12416, "closing": 17655, "candidates": 3}, "OBC": {"opening": 8294, "closing": 9206, "candidates": 2}, "OPEN": {"opening": 5470, "closing": 9183, "candidates": 2}, "SC": {"opening": 9493, "closing": 25674, "candidates": 2}}}, "CRS0196": {"categories": {"SC": {"opening": 24587, "closing": 28786, "candidates": 3}}}}}}}